{
  "themeLayoutType" : "Inner",
  "viewType" : "list",
  "appPageId" : "7f4fdac9-a1a5-4015-bf07-51969a4b2b79",
  "componentName" : "siteforce:sldsOneColLayout",
  "label" : "Record List",
  "id" : "38018963-e0e4-4bd7-8a5b-1c2dbfb8f590",
  "type" : "view",
  "regions" : [ {
    "regionName" : "header",
    "id" : "a1f5b3e1-29e2-49ce-8c76-da932e08c05d",
    "type" : "region",
    "components" : [ ]
  }, {
    "regionName" : "content",
    "id" : "e7078aca-df42-4d5d-b8d3-e2cb7a672d91",
    "type" : "region",
    "components" : [ {
      "componentName" : "forceCommunity:objectHome",
      "componentAttributes" : {
        "layout" : "FULL",
        "showDisplay" : "showall",
        "scope" : "{!objectName}",
        "showPinnedList" : "true",
        "showActionBar" : "true",
        "filterName" : "{!filterId}",
        "pageSize" : "25",
        "enableInlineEdit" : "true",
        "showSearchBar" : "true"
      },
      "renderPriority" : "NEUTRAL",
      "renditionMap" : { },
      "id" : "8a974f95-734e-46ad-ada2-7a8f27a272ee",
      "type" : "component",
      "renditions" : [ ]
    } ]
  }, {
    "regionName" : "footer",
    "id" : "feff162a-31dd-47fa-a4c0-4f688a2c2e94",
    "type" : "region",
    "components" : [ ]
  }, {
    "regionName" : "sfdcHiddenRegion",
    "id" : "2ce58e60-063d-46a4-a293-39d3e5b607be",
    "type" : "region",
    "components" : [ {
      "componentName" : "forceCommunity:seoAssistant",
      "componentAttributes" : {
        "metaTags" : "",
        "description" : "",
        "title" : ""
      },
      "renderPriority" : "NEUTRAL",
      "renditionMap" : { },
      "id" : "df76ee13-62e8-498e-9635-de1d34c43bc2",
      "type" : "component",
      "renditions" : [ ]
    } ]
  } ]
}